Metadata-Version: 2.1
Name: my_swiki
Version: 10.1.2
Summary: A program for searching and reading Wikipedia articles in multiple languages
Author: k0ng999
Author-email: baydar_14@mail.ru
License: MIT
License-File: LICENSE
